nemspy/__init__.py
nemspy/configuration.py
nemspy/interface.py
nemspy/utilities.py
nemspy/model/__init__.py
nemspy/model/atmosphere.py
nemspy/model/base.py
nemspy/model/hydrology.py
nemspy/model/ice.py
nemspy/model/ocean.py
nemspy/model/waves.py
nemspy-1.0.8.dist-info/LICENSE
nemspy-1.0.8.dist-info/METADATA
nemspy-1.0.8.dist-info/WHEEL
nemspy-1.0.8.dist-info/top_level.txt
nemspy-1.0.8.dist-info/RECORD
