Metadata-Version: 2.1
Name: nemspy
Version: 1.0.8
Summary: NEMS configuration generation
Home-page: https://github.com/noaa-ocs-modeling/nemspy.git
Author: Zach Burnett <zachary.r.burnett@gmail.com>, Jaime R Calzada <jreniel@gmail.com>
License: CC0
Platform: UNKNOWN
License-File: LICENSE
Provides-Extra: development
Requires-Dist: flake8 ; extra == 'development'
Requires-Dist: isort ; extra == 'development'
Requires-Dist: oitnb ; extra == 'development'
Provides-Extra: documentation
Requires-Dist: dunamai ; extra == 'documentation'
Requires-Dist: m2r2 ; extra == 'documentation'
Requires-Dist: sphinx ; extra == 'documentation'
Requires-Dist: sphinx-rtd-theme ; extra == 'documentation'
Provides-Extra: testing
Requires-Dist: pytest ; extra == 'testing'
Requires-Dist: pytest-cov ; extra == 'testing'
Requires-Dist: pytest-xdist ; extra == 'testing'
